{
    "KPlugin": {
        "Authors": [
            {
                "Email": "mvourlakos@gmail.com, audoban@openmailbox.org",
                "Name": "Michail Vourlakos, Smith Ar"
            }
        ],
        "Category": "",
        "Dependencies": [
        ],
        "Description": "Containment provided for the Latte Dock",
        "Description[ar]": "حاوية موفرة لرصيف لاتيه",
        "Description[az]": "Latte Dok paneli üçün təmin edilən qoruma",
        "Description[ca@valencia]": "Contenidor proporcionat per l'acoblador Latte",
        "Description[ca]": "Contenidor proporcionat per l'acoblador Latte",
        "Description[cs]": "Kontejner pro Latte Dock",
        "Description[da]": "Beholder til Latte-dokken",
        "Description[de]": "Containment für Latte-Dock",
        "Description[el]": "Περιέκτης της εφαρμογής Latte",
        "Description[en_GB]": "Containment provided for the Latte Dock",
        "Description[es]": "Contenedor proporcionada para Latte Dock",
        "Description[et]": "Latte doki konteiner",
        "Description[eu]": "Konfinamendua hornitu da Latte Dockentzako",
        "Description[fi]": "Latte-telakalla tarjottu sisällytys",
        "Description[fr]": "Confinement fourni par le panneau « Latte »",
        "Description[gl]": "Contedor fornecido para a doca Latte.",
        "Description[id]": "Kontainmen disediakan untuk Dock Latte",
        "Description[it]": "Contenitore fornito per Latte Dock",
        "Description[ko]": "Latte 독 컨테이너",
        "Description[lt]": "Latte dokui teikiamas suvaržymas",
        "Description[nl]": "Container geleverd voor de Latte Dock",
        "Description[nn]": "Behaldar for Latte-dokk",
        "Description[pl]": "Pojemnik dla doku Latte",
        "Description[pt]": "Contentor oferecido para a área acoplável do Latte",
        "Description[pt_BR]": "Contêiner fornecido pelo Latte Dock",
        "Description[ru]": "Контейнер Latte Dock",
        "Description[sl]": "Zadrževalni prostor za Latte dok",
        "Description[sv]": "Omgivning tillhandahållen för Latte dockningsfönster",
        "Description[uk]": "Контейнер панелі Латте",
        "Description[x-test]": "xxContainment provided for the Latte Dockxx",
        "Description[zh_CN]": "用于 Latte 停靠栏的容器",
        "Description[zh_TW]": "提供 Latte Dock 使用的容器",
        "EnabledByDefault": true,
        "Id": "org.kde.latte.containment",
        "License": "GPL",
        "Name": "Latte Containment",
        "Name[ar]": "حاوية لاتيه",
        "Name[az]": "Latte əhatəsi",
        "Name[ca@valencia]": "Contenidor de Latte",
        "Name[ca]": "Contenidor del Latte",
        "Name[cs]": "Kontejner Latte",
        "Name[en_GB]": "Latte Containment",
        "Name[es]": "Contenedor de Latte",
        "Name[fi]": "Latte-säilö",
        "Name[fr]": "Conteneur pour Latte",
        "Name[it]": "Contenitore di Latte",
        "Name[ko]": "Latte 컨테이너",
        "Name[lt]": "Latte suvaržymas",
        "Name[nl]": "Latte-container",
        "Name[pl]": "Pojemnik Latte",
        "Name[pt]": "Contentor do Latte",
        "Name[pt_BR]": "Contêiner do Latte",
        "Name[sk]": "Latte Containment",
        "Name[sl]": "Latte zadrževalnik",
        "Name[sv]": "Latte-omgivning",
        "Name[uk]": "контейнер Латте",
        "Name[x-test]": "xxLatte Containmentxx",
        "Name[zh_CN]": "Latte 容器",
        "Name[zh_TW]": "Latte Containment",
        "ServiceTypes": [
            "Plasma/Applet",
            "Plasma/Containment"
        ],
        "Website": "https://userbase.kde.org/LatteDock"
    },
    "NoDisplay": true,
    "X-Plasma-API": "declarativeappletscript",
    "X-Plasma-ContainmentType": "Panel",
    "X-Plasma-MainScript": "ui/main.qml"
}
